skill_directory/LICENSE.md
skill_directory/README.md
skill_directory/__init__.py
skill_directory/request_handling.py
skill_directory/skill.json
skill_directory/version.py
skill_directory/version_bump.py
skill_directory/locale/en-us/run_mall_parser.intent
skill_directory/locale/en-us/dialog/en/all_locations.dialog
skill_directory/locale/en-us/dialog/en/another_shop.dialog
skill_directory/locale/en-us/dialog/en/ask_more.dialog
skill_directory/locale/en-us/dialog/en/choose_selection.dialog
skill_directory/locale/en-us/dialog/en/closed_now.dialog
skill_directory/locale/en-us/dialog/en/closing_minutes.dialog
skill_directory/locale/en-us/dialog/en/finished.dialog
skill_directory/locale/en-us/dialog/en/found_shop.dialog
skill_directory/locale/en-us/dialog/en/more_than_one.dialog
skill_directory/locale/en-us/dialog/en/no_lang.dialog
skill_directory/locale/en-us/dialog/en/no_shop_on_level.dialog
skill_directory/locale/en-us/dialog/en/no_shop_request.dialog
skill_directory/locale/en-us/dialog/en/open_now.dialog
skill_directory/locale/en-us/dialog/en/opening_hours.dialog
skill_directory/locale/en-us/dialog/en/opening_minutes.dialog
skill_directory/locale/en-us/dialog/en/shop_by_floor.dialog
skill_directory/locale/en-us/dialog/en/shop_not_found.dialog
skill_directory/locale/en-us/dialog/en/start_parsing.dialog
skill_directory/locale/en-us/dialog/en/stop.dialog
skill_directory/locale/en-us/dialog/en/unexpected_error.dialog
skill_directory/locale/en-us/dialog/en/which_floor.dialog
skill_directory/locale/en-us/vocab/en/location.voc
skill_directory/locale/en-us/vocab/en/no.voc
skill_directory/locale/en-us/vocab/en/time.voc
skill_directory/locale/en-us/vocab/en/yes.voc
skill_directory/neon_skill_directory.egg-info/PKG-INFO
skill_directory/neon_skill_directory.egg-info/SOURCES.txt
skill_directory/neon_skill_directory.egg-info/dependency_links.txt
skill_directory/neon_skill_directory.egg-info/entry_points.txt
skill_directory/neon_skill_directory.egg-info/requires.txt
skill_directory/neon_skill_directory.egg-info/top_level.txt
skill_directory/test/test_skill.py
neon_skill_directory-0.0.1a3.dist-info/LICENSE.md
neon_skill_directory-0.0.1a3.dist-info/METADATA
neon_skill_directory-0.0.1a3.dist-info/WHEEL
neon_skill_directory-0.0.1a3.dist-info/entry_points.txt
neon_skill_directory-0.0.1a3.dist-info/top_level.txt
neon_skill_directory-0.0.1a3.dist-info/RECORD
