Metadata-Version: 2.1
Name: neon-skill-directory
Version: 0.0.1a3
Summary: UNKNOWN
Home-page: https://github.com/NeonGeckoCom/skill-directory
Author: Neongecko
Author-email: developers@neon.ai
License: BSD-3-Clause
Platform: UNKNOWN
Requires-Dist: numpy
Requires-Dist: neon-utils (~=1.0)
Requires-Dist: bs4
Requires-Dist: requests
Requires-Dist: ovos-lingua-franca
Requires-Dist: datetime
